wand/__init__.py
wand/api.py
wand/assertions.py
wand/color.py
wand/compat.py
wand/display.py
wand/drawing.py
wand/exceptions.py
wand/font.py
wand/image.py
wand/resource.py
wand/sequence.py
wand/version.py
wand/cdefs/__init__.py
wand/cdefs/core.py
wand/cdefs/drawing_wand.py
wand/cdefs/magick_image.py
wand/cdefs/magick_property.py
wand/cdefs/magick_wand.py
wand/cdefs/pixel_iterator.py
wand/cdefs/pixel_wand.py
wand/cdefs/structures.py
wand/cdefs/wandtypes.py
Wand-0.6.13.dist-info/LICENSE
Wand-0.6.13.dist-info/METADATA
Wand-0.6.13.dist-info/WHEEL
Wand-0.6.13.dist-info/top_level.txt
Wand-0.6.13.dist-info/RECORD
